easy_pyweb/README.MD
easy_pyweb/__init__.py
easy_pyweb/more_tool.py
easy_pyweb/sql_helpers.py
easy_pyweb/wb_helpers.py
easy_pyweb/windows_tool.py
easy_pyweb/js/stealth.min.js
easy_pyweb-1.3.dist-info/LICENSE
easy_pyweb-1.3.dist-info/METADATA
easy_pyweb-1.3.dist-info/WHEEL
easy_pyweb-1.3.dist-info/top_level.txt
easy_pyweb-1.3.dist-info/RECORD
