Metadata-Version: 2.1
Name: easy_pyweb
Version: 1.3
Summary: web helper
Home-page: https://github.com/xiaoxigithub
Author: xiaoxi
Author-email: xiaoxiggnet@gmail.com
Requires-Python: >=3.6
License-File: LICENSE
Requires-Dist: requests
Requires-Dist: playwright
